vman3_dq/__init__.py
vman3_dq/core.py
vman3_dq/utils.py
vman3_dq/data/__init__.py
vman3_dq/data/dictionary.csv
vman3_dq/data/sample_data.csv
vman3_dq-0.1.1.dist-info/licenses/LICENSE
vman3_dq-0.1.1.dist-info/METADATA
vman3_dq-0.1.1.dist-info/WHEEL
vman3_dq-0.1.1.dist-info/top_level.txt
vman3_dq-0.1.1.dist-info/RECORD
